<?xml version="1.0"?>
<Category ItemCount="1" Name="Derived Data Formulas">
  <Item PropertyCount="1" CodeType="Calculation" Code="Reference Price FA MCC Equities" Database="\\MZTSBATCH01\PUBLIC_GOLD">
    <Property Name="Calculation" Static="true" MultiSourced="false" DataType="Formula">
      <Xenomorph.Generic.Formula RowColumnFormat="A1" CellDefinitionsRows="64" CellDefinitionsColumns="5">
        <NamedRanges>
          <CellNameDefinition Name="AdjustCodeForGREquity">
            <Range Top="29" Left="1" Bottom="29" Right="1" />
          </CellNameDefinition>
          <CellNameDefinition Name="Ask">
            <Range Top="41" Left="1" Bottom="41" Right="1" />
          </CellNameDefinition>
          <CellNameDefinition Name="Bid">
            <Range Top="42" Left="1" Bottom="42" Right="1" />
          </CellNameDefinition>
          <CellNameDefinition Name="CodeName">
            <Range Top="3" Left="1" Bottom="3" Right="1" />
          </CellNameDefinition>
          <CellNameDefinition Name="CodeTypeName">
            <Range Top="4" Left="1" Bottom="4" Right="1" />
          </CellNameDefinition>
          <CellNameDefinition Name="Counterparty">
            <Range Top="20" Left="1" Bottom="20" Right="1" />
          </CellNameDefinition>
          <CellNameDefinition Name="Currency">
            <Range Top="22" Left="1" Bottom="22" Right="1" />
          </CellNameDefinition>
          <CellNameDefinition Name="DatabaseName">
            <Range Top="2" Left="1" Bottom="2" Right="1" />
          </CellNameDefinition>
          <CellNameDefinition Name="EndDate">
            <Range Top="7" Left="1" Bottom="7" Right="1" />
          </CellNameDefinition>
          <CellNameDefinition Name="EndDateTime">
            <Range Top="19" Left="1" Bottom="19" Right="1" />
          </CellNameDefinition>
          <CellNameDefinition Name="EOD">
            <Range Top="40" Left="3" Bottom="40" Right="3" />
          </CellNameDefinition>
          <CellNameDefinition Name="ETFCode">
            <Range Top="35" Left="1" Bottom="35" Right="1" />
          </CellNameDefinition>
          <CellNameDefinition Name="FormulaResult">
            <Range Top="0" Left="0" Bottom="0" Right="0" />
          </CellNameDefinition>
          <CellNameDefinition Name="FuturesCode">
            <Range Top="34" Left="1" Bottom="34" Right="1" />
          </CellNameDefinition>
          <CellNameDefinition Name="HistPrice">
            <Range Top="42" Left="3" Bottom="42" Right="3" />
          </CellNameDefinition>
          <CellNameDefinition Name="InputAudit">
            <Range Top="63" Left="1" Bottom="63" Right="1" />
          </CellNameDefinition>
          <CellNameDefinition Name="Instrument">
            <Range Top="21" Left="1" Bottom="21" Right="1" />
          </CellNameDefinition>
          <CellNameDefinition Name="IsGREquity">
            <Range Top="27" Left="1" Bottom="27" Right="1" />
          </CellNameDefinition>
          <CellNameDefinition Name="ISIN">
            <Range Top="23" Left="1" Bottom="23" Right="1" />
          </CellNameDefinition>
          <CellNameDefinition Name="MappingTable">
            <Range Top="26" Left="1" Bottom="26" Right="1" />
          </CellNameDefinition>
          <CellNameDefinition Name="MappingTableStockcode">
            <Range Top="28" Left="1" Bottom="28" Right="1" />
          </CellNameDefinition>
          <CellNameDefinition Name="Market">
            <Range Top="24" Left="1" Bottom="24" Right="1" />
          </CellNameDefinition>
          <CellNameDefinition Name="MarketData">
            <Range Top="52" Left="1" Bottom="52" Right="1" />
          </CellNameDefinition>
          <CellNameDefinition Name="MarketDataCode">
            <Range Top="36" Left="1" Bottom="36" Right="1" />
          </CellNameDefinition>
          <CellNameDefinition Name="MarketDataEndTime">
            <Range Top="40" Left="1" Bottom="40" Right="1" />
          </CellNameDefinition>
          <CellNameDefinition Name="MarketDataItem">
            <Range Top="38" Left="1" Bottom="38" Right="1" />
          </CellNameDefinition>
          <CellNameDefinition Name="MarketDataSource">
            <Range Top="37" Left="1" Bottom="37" Right="1" />
          </CellNameDefinition>
          <CellNameDefinition Name="MarketdataStartTime">
            <Range Top="39" Left="1" Bottom="39" Right="1" />
          </CellNameDefinition>
          <CellNameDefinition Name="MaxAsk">
            <Range Top="43" Left="1" Bottom="43" Right="1" />
          </CellNameDefinition>
          <CellNameDefinition Name="MaximumAge">
            <Range Top="10" Left="1" Bottom="10" Right="1" />
          </CellNameDefinition>
          <CellNameDefinition Name="MinBid">
            <Range Top="44" Left="1" Bottom="44" Right="1" />
          </CellNameDefinition>
          <CellNameDefinition Name="OptionCode">
            <Range Top="33" Left="1" Bottom="33" Right="1" />
          </CellNameDefinition>
          <CellNameDefinition Name="QIAsk">
            <Range Top="58" Left="3" Bottom="58" Right="3" />
          </CellNameDefinition>
          <CellNameDefinition Name="QIBid">
            <Range Top="60" Left="3" Bottom="60" Right="3" />
          </CellNameDefinition>
          <CellNameDefinition Name="QualityAsk">
            <Range Top="47" Left="1" Bottom="47" Right="1" />
          </CellNameDefinition>
          <CellNameDefinition Name="QualityBid">
            <Range Top="48" Left="1" Bottom="48" Right="1" />
          </CellNameDefinition>
          <CellNameDefinition Name="ReferenceValue ">
            <Range Top="0" Left="0" Bottom="0" Right="0" />
          </CellNameDefinition>
          <CellNameDefinition Name="RequestItem">
            <Range Top="17" Left="1" Bottom="17" Right="1" />
          </CellNameDefinition>
          <CellNameDefinition Name="RequestItemCode">
            <Range Top="12" Left="1" Bottom="12" Right="1" />
          </CellNameDefinition>
          <CellNameDefinition Name="Results">
            <Range Top="52" Left="0" Bottom="61" Right="2" />
          </CellNameDefinition>
          <CellNameDefinition Name="StartDate">
            <Range Top="6" Left="1" Bottom="6" Right="1" />
          </CellNameDefinition>
          <CellNameDefinition Name="StartDateTime">
            <Range Top="18" Left="1" Bottom="18" Right="1" />
          </CellNameDefinition>
          <CellNameDefinition Name="StockCode">
            <Range Top="31" Left="1" Bottom="31" Right="1" />
          </CellNameDefinition>
          <CellNameDefinition Name="TargetDataSource">
            <Range Top="8" Left="1" Bottom="8" Right="1" />
          </CellNameDefinition>
          <CellNameDefinition Name="TargetProperty">
            <Range Top="5" Left="1" Bottom="5" Right="1" />
          </CellNameDefinition>
          <CellNameDefinition Name="TradeDateTime">
            <Range Top="16" Left="1" Bottom="16" Right="1" />
          </CellNameDefinition>
          <CellNameDefinition Name="Tradeitem">
            <Range Top="15" Left="1" Bottom="15" Right="1" />
          </CellNameDefinition>
          <CellNameDefinition Name="TradeQuotesMax">
            <Range Top="45" Left="1" Bottom="45" Right="1" />
          </CellNameDefinition>
          <CellNameDefinition Name="TradeQuotesMin">
            <Range Top="46" Left="1" Bottom="46" Right="1" />
          </CellNameDefinition>
          <CellNameDefinition Name="TradeType">
            <Range Top="11" Left="1" Bottom="11" Right="1" />
          </CellNameDefinition>
          <CellNameDefinition Name="WarrantCode">
            <Range Top="32" Left="1" Bottom="32" Right="1" />
          </CellNameDefinition>
        </NamedRanges>
        <Cells>
          <CellDefinition p6:type="FormulaCellDefinition" CalculationEnabled="true" DataVisible="true" RowHidden="false" EndOfLine="false" xmlns:p6="http://www.w3.org/2001/XMLSchema-instance">
            <Range Top="29" Left="1" Bottom="29" Right="1" />
            <Value>MappingTableStockcode.REPLACE(  " GY ", " GR " )</Value>
          </CellDefinition>
          <CellDefinition p6:type="FormulaCellDefinition" CalculationEnabled="true" DataVisible="true" RowHidden="false" EndOfLine="false" xmlns:p6="http://www.w3.org/2001/XMLSchema-instance">
            <Range Top="41" Left="1" Bottom="41" Right="1" />
            <Value>MarketDataItem.Ask IntraDay.Data(MarketdataStartTime,MarketDataEndTime)</Value>
          </CellDefinition>
          <CellDefinition p6:type="FormulaCellDefinition" CalculationEnabled="true" DataVisible="true" RowHidden="false" EndOfLine="false" xmlns:p6="http://www.w3.org/2001/XMLSchema-instance">
            <Range Top="42" Left="1" Bottom="42" Right="1" />
            <Value>MarketDataItem.Bid IntraDay.Data(MarketdataStartTime,MarketDataEndTime)</Value>
          </CellDefinition>
          <CellDefinition p6:type="ConstantCellDefinition" CalculationEnabled="true" DataVisible="true" RowHidden="false" EndOfLine="false" xmlns:p6="http://www.w3.org/2001/XMLSchema-instance">
            <Range Top="3" Left="1" Bottom="3" Right="1" />
            <Value xmlns:q1="http://www.w3.org/2001/XMLSchema" p6:type="q1:string">2711291_Buy</Value>
          </CellDefinition>
          <CellDefinition p6:type="ConstantCellDefinition" CalculationEnabled="true" DataVisible="true" RowHidden="false" EndOfLine="false" xmlns:p6="http://www.w3.org/2001/XMLSchema-instance">
            <Range Top="4" Left="1" Bottom="4" Right="1" />
            <Value xmlns:q2="http://www.w3.org/2001/XMLSchema" p6:type="q2:string">Front Arena Trade</Value>
          </CellDefinition>
          <CellDefinition p6:type="FormulaCellDefinition" CalculationEnabled="true" DataVisible="true" RowHidden="false" EndOfLine="false" xmlns:p6="http://www.w3.org/2001/XMLSchema-instance">
            <Range Top="20" Left="1" Bottom="20" Right="1" />
            <Value>Tradeitem.Counterparty</Value>
          </CellDefinition>
          <CellDefinition p6:type="FormulaCellDefinition" CalculationEnabled="true" DataVisible="true" RowHidden="false" EndOfLine="false" xmlns:p6="http://www.w3.org/2001/XMLSchema-instance">
            <Range Top="22" Left="1" Bottom="22" Right="1" />
            <Value>Tradeitem.Currency.Code</Value>
          </CellDefinition>
          <CellDefinition p6:type="ConstantCellDefinition" CalculationEnabled="true" DataVisible="true" RowHidden="false" EndOfLine="false" xmlns:p6="http://www.w3.org/2001/XMLSchema-instance">
            <Range Top="2" Left="1" Bottom="2" Right="1" />
            <Value xmlns:q3="http://www.w3.org/2001/XMLSchema" p6:type="q3:string">MD_SILVER</Value>
          </CellDefinition>
          <CellDefinition p6:type="ConstantCellDefinition" CalculationEnabled="true" DataVisible="true" RowHidden="false" EndOfLine="false" xmlns:p6="http://www.w3.org/2001/XMLSchema-instance">
            <Range Top="7" Left="1" Bottom="7" Right="1" />
            <Value xmlns:q4="http://www.w3.org/2001/XMLSchema" p6:type="q4:dateTime">2018-11-29T00:00:00</Value>
          </CellDefinition>
          <CellDefinition p6:type="FormulaCellDefinition" CalculationEnabled="true" DataVisible="true" RowHidden="false" EndOfLine="false" xmlns:p6="http://www.w3.org/2001/XMLSchema-instance">
            <Range Top="19" Left="1" Bottom="19" Right="1" />
            <Value>RequestItem.|End DateTime|</Value>
          </CellDefinition>
          <CellDefinition p6:type="FormulaCellDefinition" CalculationEnabled="true" DataVisible="true" RowHidden="false" EndOfLine="false" xmlns:p6="http://www.w3.org/2001/XMLSchema-instance">
            <Range Top="40" Left="3" Bottom="40" Right="3" />
            <Value>DATEADD(C40, E41)</Value>
          </CellDefinition>
          <CellDefinition p6:type="FormulaCellDefinition" CalculationEnabled="true" DataVisible="true" RowHidden="false" EndOfLine="false" xmlns:p6="http://www.w3.org/2001/XMLSchema-instance">
            <Range Top="35" Left="1" Bottom="35" Right="1" />
            <Value>IF(TradeType='ETF',MappingTable.Where(Column_2 =Currency
AND Column_3 =ISIN
AND Column_4 =Market
).Column_5,'')</Value>
          </CellDefinition>
          <CellDefinition p6:type="FormulaCellDefinition" CalculationEnabled="true" DataVisible="true" RowHidden="false" EndOfLine="false" xmlns:p6="http://www.w3.org/2001/XMLSchema-instance">
            <Range Top="0" Left="0" Bottom="0" Right="0" />
            <Value>Results.Values(Column_1,Column_2)</Value>
          </CellDefinition>
          <CellDefinition p6:type="FormulaCellDefinition" CalculationEnabled="true" DataVisible="true" RowHidden="false" EndOfLine="false" xmlns:p6="http://www.w3.org/2001/XMLSchema-instance">
            <Range Top="34" Left="1" Bottom="34" Right="1" />
            <Value>IF(TradeType ='Futures',Item('Public_GOLD',
'Calculate Bloomberg IPV Futures Codes','Calculation')
.calculation
.setvalues('DatabaseName',DatabaseName,'CodeName',CodeName,'CodeTypeName',CodeTypeName)
.Values(IfIndexFuture).Column_1,'')</Value>
          </CellDefinition>
          <CellDefinition p6:type="FormulaCellDefinition" CalculationEnabled="true" DataVisible="true" RowHidden="false" EndOfLine="false" xmlns:p6="http://www.w3.org/2001/XMLSchema-instance">
            <Range Top="42" Left="3" Bottom="42" Right="3" />
            <Value>MarketDataItem.Values(|Ask Intraday|,|Bid Intraday|.Data(MarketdataStartTime,EOD))</Value>
          </CellDefinition>
          <CellDefinition p6:type="FormulaCellDefinition" CalculationEnabled="true" DataVisible="true" RowHidden="false" EndOfLine="false" xmlns:p6="http://www.w3.org/2001/XMLSchema-instance">
            <Range Top="63" Left="1" Bottom="63" Right="1" />
            <Value>Results.Values(Column_1,Column_3)</Value>
          </CellDefinition>
          <CellDefinition p6:type="FormulaCellDefinition" CalculationEnabled="true" DataVisible="true" RowHidden="false" EndOfLine="false" xmlns:p6="http://www.w3.org/2001/XMLSchema-instance">
            <Range Top="21" Left="1" Bottom="21" Right="1" />
            <Value>Tradeitem.Instrument</Value>
          </CellDefinition>
          <CellDefinition p6:type="FormulaCellDefinition" CalculationEnabled="true" DataVisible="true" RowHidden="false" EndOfLine="false" xmlns:p6="http://www.w3.org/2001/XMLSchema-instance">
            <Range Top="27" Left="1" Bottom="27" Right="1" />
            <Value>IF(Market = 'XETRA' AND Counterparty &lt;&gt; 'XETRA',TRUE,FALSE)</Value>
          </CellDefinition>
          <CellDefinition p6:type="FormulaCellDefinition" CalculationEnabled="true" DataVisible="true" RowHidden="false" EndOfLine="false" xmlns:p6="http://www.w3.org/2001/XMLSchema-instance">
            <Range Top="23" Left="1" Bottom="23" Right="1" />
            <Value>IF(TradeType = 'HLB Warrant',Tradeitem.|ISIN Underlying|.Code,
Tradeitem.|ISIN|.Code)</Value>
          </CellDefinition>
          <CellDefinition p6:type="FormulaCellDefinition" CalculationEnabled="true" DataVisible="true" RowHidden="false" EndOfLine="false" xmlns:p6="http://www.w3.org/2001/XMLSchema-instance">
            <Range Top="26" Left="1" Bottom="26" Right="1" />
            <Value>Item('\\MZTSBATCH01\PUBLIC_GOLD','FA EQ MCC','Mapping Table').Table</Value>
          </CellDefinition>
          <CellDefinition p6:type="FormulaCellDefinition" CalculationEnabled="true" DataVisible="true" RowHidden="false" EndOfLine="false" xmlns:p6="http://www.w3.org/2001/XMLSchema-instance">
            <Range Top="28" Left="1" Bottom="28" Right="1" />
            <Value>MappingTable.Where(Column_1 =Instrument
AND Column_2 =Currency
AND Column_3 =ISIN
AND Column_4 =Market
).Column_5</Value>
          </CellDefinition>
          <CellDefinition p6:type="FormulaCellDefinition" CalculationEnabled="true" DataVisible="true" RowHidden="false" EndOfLine="false" xmlns:p6="http://www.w3.org/2001/XMLSchema-instance">
            <Range Top="24" Left="1" Bottom="24" Right="1" />
            <Value>Tradeitem.|Front Arena Market|</Value>
          </CellDefinition>
          <CellDefinition p6:type="FormulaCellDefinition" CalculationEnabled="true" DataVisible="true" RowHidden="false" EndOfLine="false" xmlns:p6="http://www.w3.org/2001/XMLSchema-instance">
            <Range Top="52" Left="1" Bottom="52" Right="1" />
            <Value>IF(ISERROR(MarketDataItem),NULL,MarketDataItem)</Value>
          </CellDefinition>
          <CellDefinition p6:type="FormulaCellDefinition" CalculationEnabled="true" DataVisible="true" RowHidden="false" EndOfLine="false" xmlns:p6="http://www.w3.org/2001/XMLSchema-instance">
            <Range Top="36" Left="1" Bottom="36" Right="1" />
            <Value>IF(TradeType='Listed Option',OptionCode,
IF(TradeType = 'Common Stock',StockCode,
IF(TradeType= 'HLB Warrant',WarrantCode,
IF(TradeType = 'ETF',ETFCode,
IF(TradeType = 'Futures',FuturesCode,'')))))</Value>
          </CellDefinition>
          <CellDefinition p6:type="FormulaCellDefinition" CalculationEnabled="true" DataVisible="true" RowHidden="false" EndOfLine="false" xmlns:p6="http://www.w3.org/2001/XMLSchema-instance">
            <Range Top="40" Left="1" Bottom="40" Right="1" />
            <Value>TradeDateTime</Value>
          </CellDefinition>
          <CellDefinition p6:type="FormulaCellDefinition" CalculationEnabled="true" DataVisible="true" RowHidden="false" EndOfLine="false" xmlns:p6="http://www.w3.org/2001/XMLSchema-instance">
            <Range Top="38" Left="1" Bottom="38" Right="1" />
            <Value>Item(DatabaseName,
MarketDataCode,
'Bloomberg')</Value>
          </CellDefinition>
          <CellDefinition p6:type="FormulaCellDefinition" CalculationEnabled="true" DataVisible="true" RowHidden="false" EndOfLine="false" xmlns:p6="http://www.w3.org/2001/XMLSchema-instance">
            <Range Top="37" Left="1" Bottom="37" Right="1" />
            <Value>IF(TradeType = 'Common Stock',
IF(IsGREquity,'GR',MarketDataCode.SPLIT(' ')[2]),
'Bloomberg')</Value>
          </CellDefinition>
          <CellDefinition p6:type="FormulaCellDefinition" CalculationEnabled="true" DataVisible="true" RowHidden="false" EndOfLine="false" xmlns:p6="http://www.w3.org/2001/XMLSchema-instance">
            <Range Top="39" Left="1" Bottom="39" Right="1" />
            <Value>TradeDateTime.DATEADD(MaximumAge)</Value>
          </CellDefinition>
          <CellDefinition p6:type="FormulaCellDefinition" CalculationEnabled="true" DataVisible="true" RowHidden="false" EndOfLine="false" xmlns:p6="http://www.w3.org/2001/XMLSchema-instance">
            <Range Top="43" Left="1" Bottom="43" Right="1" />
            <Value>Ask.MAX()</Value>
          </CellDefinition>
          <CellDefinition p6:type="ConstantCellDefinition" CalculationEnabled="true" DataVisible="true" RowHidden="false" EndOfLine="false" xmlns:p6="http://www.w3.org/2001/XMLSchema-instance">
            <Range Top="10" Left="1" Bottom="10" Right="1" />
            <Value xmlns:q5="http://www.w3.org/2001/XMLSchema" p6:type="q5:string">-12H</Value>
          </CellDefinition>
          <CellDefinition p6:type="FormulaCellDefinition" CalculationEnabled="true" DataVisible="true" RowHidden="false" EndOfLine="false" xmlns:p6="http://www.w3.org/2001/XMLSchema-instance">
            <Range Top="44" Left="1" Bottom="44" Right="1" />
            <Value>Bid.MIN()</Value>
          </CellDefinition>
          <CellDefinition p6:type="FormulaCellDefinition" CalculationEnabled="true" DataVisible="true" RowHidden="false" EndOfLine="false" xmlns:p6="http://www.w3.org/2001/XMLSchema-instance">
            <Range Top="33" Left="1" Bottom="33" Right="1" />
            <Value>IF(TradeType = 'Listed Option',Item('Public_GOLD','Calculate Bloomberg IPV Listed Options Codes','calculation')
.calculation
.setvalues('DatabaseName',DatabaseName,'CodeName',CodeName,'CodeTypeName',CodeTypeName)
.Values(BBGTicker).Column_1,'')</Value>
          </CellDefinition>
          <CellDefinition CalculationEnabled="true" DataVisible="true" RowHidden="true" EndOfLine="false">
            <Range Top="58" Left="3" Bottom="58" Right="3" />
          </CellDefinition>
          <CellDefinition CalculationEnabled="true" DataVisible="true" RowHidden="false" EndOfLine="false">
            <Range Top="60" Left="3" Bottom="60" Right="3" />
          </CellDefinition>
          <CellDefinition p6:type="FormulaCellDefinition" CalculationEnabled="true" DataVisible="true" RowHidden="false" EndOfLine="false" xmlns:p6="http://www.w3.org/2001/XMLSchema-instance">
            <Range Top="47" Left="1" Bottom="47" Right="1" />
            <Value>Item('PUBLIC_GOLD', 'Calculate QI 5D From Market data History', 'Calculation' ).CalculatiON.SetValues( 'DailyTimeSeries', MarketDataItem.End of Day Ask, 'TodaysPrice', MaxAsk ).GetValues( 'QualityIndex', 'QualityIndexCalculation' )</Value>
          </CellDefinition>
          <CellDefinition p6:type="FormulaCellDefinition" CalculationEnabled="true" DataVisible="true" RowHidden="false" EndOfLine="false" xmlns:p6="http://www.w3.org/2001/XMLSchema-instance">
            <Range Top="48" Left="1" Bottom="48" Right="1" />
            <Value>Item('PUBLIC_GOLD', 'Calculate QI 5D From Market data History', 'Calculation' ).CalculatiON.SetValues( 'DailyTimeSeries', MarketDataItem.End of Day Bid, 'TodaysPrice', MinBid ).GetValues( 'QualityIndex', 'QualityIndexCalculation')</Value>
          </CellDefinition>
          <CellDefinition p6:type="FormulaCellDefinition" CalculationEnabled="true" DataVisible="true" RowHidden="false" EndOfLine="false" xmlns:p6="http://www.w3.org/2001/XMLSchema-instance">
            <Range Top="17" Left="1" Bottom="17" Right="1" />
            <Value>Item(DatabaseName,RequestItemCode, "Bloomberg Request")</Value>
          </CellDefinition>
          <CellDefinition p6:type="FormulaCellDefinition" CalculationEnabled="true" DataVisible="true" RowHidden="false" EndOfLine="false" xmlns:p6="http://www.w3.org/2001/XMLSchema-instance">
            <Range Top="12" Left="1" Bottom="12" Right="1" />
            <Value>StartDate.TOSTRING("yyyyMMdd") + "_" + CodeName</Value>
          </CellDefinition>
          <CellDefinition p6:type="ConstantCellDefinition" CalculationEnabled="true" DataVisible="true" RowHidden="false" EndOfLine="false" xmlns:p6="http://www.w3.org/2001/XMLSchema-instance">
            <Range Top="52" Left="0" Bottom="52" Right="0" />
            <Value xmlns:q6="http://www.w3.org/2001/XMLSchema" p6:type="q6:string">Market Data</Value>
          </CellDefinition>
          <CellDefinition p6:type="FormulaCellDefinition" CalculationEnabled="true" DataVisible="true" RowHidden="false" EndOfLine="false" xmlns:p6="http://www.w3.org/2001/XMLSchema-instance">
            <Range Top="61" Left="2" Bottom="61" Right="2" />
            <Value>Values(DatabaseName,CodeName,CodeTypeName,'Trade Price','Front Arena',StartDate)</Value>
          </CellDefinition>
          <CellDefinition p6:type="ConstantCellDefinition" CalculationEnabled="true" DataVisible="true" RowHidden="false" EndOfLine="false" xmlns:p6="http://www.w3.org/2001/XMLSchema-instance">
            <Range Top="6" Left="1" Bottom="6" Right="1" />
            <Value xmlns:q7="http://www.w3.org/2001/XMLSchema" p6:type="q7:dateTime">2018-11-29T00:00:00</Value>
          </CellDefinition>
          <CellDefinition p6:type="FormulaCellDefinition" CalculationEnabled="true" DataVisible="true" RowHidden="false" EndOfLine="false" xmlns:p6="http://www.w3.org/2001/XMLSchema-instance">
            <Range Top="18" Left="1" Bottom="18" Right="1" />
            <Value>RequestItem.|Start DateTime|</Value>
          </CellDefinition>
          <CellDefinition p6:type="FormulaCellDefinition" CalculationEnabled="true" DataVisible="true" RowHidden="false" EndOfLine="false" xmlns:p6="http://www.w3.org/2001/XMLSchema-instance">
            <Range Top="31" Left="1" Bottom="31" Right="1" />
            <Value>IF(TradeType = 'Common Stock',
IF(IsGREquity,AdjustCodeForGREquity,MappingTableStockcode),
'')</Value>
          </CellDefinition>
          <CellDefinition p6:type="ConstantCellDefinition" CalculationEnabled="true" DataVisible="true" RowHidden="false" EndOfLine="false" xmlns:p6="http://www.w3.org/2001/XMLSchema-instance">
            <Range Top="8" Left="1" Bottom="8" Right="1" />
            <Value xmlns:q8="http://www.w3.org/2001/XMLSchema" p6:type="q8:string">Front Arena Trades</Value>
          </CellDefinition>
          <CellDefinition p6:type="ConstantCellDefinition" CalculationEnabled="true" DataVisible="true" RowHidden="false" EndOfLine="false" xmlns:p6="http://www.w3.org/2001/XMLSchema-instance">
            <Range Top="5" Left="1" Bottom="5" Right="1" />
            <Value xmlns:q9="http://www.w3.org/2001/XMLSchema" p6:type="q9:string">End-Of-Day PnL</Value>
          </CellDefinition>
          <CellDefinition p6:type="FormulaCellDefinition" CalculationEnabled="true" DataVisible="true" RowHidden="false" EndOfLine="false" xmlns:p6="http://www.w3.org/2001/XMLSchema-instance">
            <Range Top="16" Left="1" Bottom="16" Right="1" />
            <Value>Tradeitem.Trade DateTime</Value>
          </CellDefinition>
          <CellDefinition p6:type="FormulaCellDefinition" CalculationEnabled="true" DataVisible="true" RowHidden="false" EndOfLine="false" xmlns:p6="http://www.w3.org/2001/XMLSchema-instance">
            <Range Top="15" Left="1" Bottom="15" Right="1" />
            <Value>Item(DatabaseName,CodeName,CodeTypeName)</Value>
          </CellDefinition>
          <CellDefinition p6:type="FormulaCellDefinition" CalculationEnabled="true" DataVisible="true" RowHidden="false" EndOfLine="false" xmlns:p6="http://www.w3.org/2001/XMLSchema-instance">
            <Range Top="45" Left="1" Bottom="45" Right="1" />
            <Value>MarketDataItem.|Trade Intraday|.Data(StartDateTime, EndDateTime).MAX()</Value>
          </CellDefinition>
          <CellDefinition p6:type="FormulaCellDefinition" CalculationEnabled="true" DataVisible="true" RowHidden="false" EndOfLine="false" xmlns:p6="http://www.w3.org/2001/XMLSchema-instance">
            <Range Top="46" Left="1" Bottom="46" Right="1" />
            <Value>MarketDataItem.|Trade Intraday|.Data(StartDateTime, EndDateTime).MIN()</Value>
          </CellDefinition>
          <CellDefinition p6:type="ConstantCellDefinition" CalculationEnabled="true" DataVisible="true" RowHidden="false" EndOfLine="false" xmlns:p6="http://www.w3.org/2001/XMLSchema-instance">
            <Range Top="11" Left="1" Bottom="11" Right="1" />
            <Value xmlns:q10="http://www.w3.org/2001/XMLSchema" p6:type="q10:string">HLB Warrant</Value>
          </CellDefinition>
          <CellDefinition p6:type="FormulaCellDefinition" CalculationEnabled="true" DataVisible="true" RowHidden="false" EndOfLine="false" xmlns:p6="http://www.w3.org/2001/XMLSchema-instance">
            <Range Top="32" Left="1" Bottom="32" Right="1" />
            <Value>IF(TradeType = 'HLB Warrant',
Tradeitem.|ISIN Underlying|.Code,'')</Value>
          </CellDefinition>
          <CellDefinition CalculationEnabled="true" DataVisible="true" RowHidden="false" EndOfLine="false">
            <Range Top="39" Left="2" Bottom="39" Right="2" />
          </CellDefinition>
          <CellDefinition p6:type="ConstantCellDefinition" CalculationEnabled="true" DataVisible="true" RowHidden="false" EndOfLine="false" xmlns:p6="http://www.w3.org/2001/XMLSchema-instance">
            <Range Top="40" Left="4" Bottom="40" Right="4" />
            <Value xmlns:q11="http://www.w3.org/2001/XMLSchema" p6:type="q11:string">-5WD</Value>
          </CellDefinition>
          <CellDefinition p6:type="FormulaCellDefinition" CalculationEnabled="true" DataVisible="true" RowHidden="false" EndOfLine="false" xmlns:p6="http://www.w3.org/2001/XMLSchema-instance">
            <Range Top="52" Left="2" Bottom="52" Right="2" />
            <Value>Values(
Values(DatabaseName,CodeName,CodeTypeName,'TradeDateTime','Front Arena',StartDate),
Values(DatabaseName,CodeName,CodeTypeName,'CounterPArty','Front Arena',StartDate),
Values(DatabaseName,CodeName,CodeTypeName,'Instrument','Front Arena',StartDate),
Values(DatabaseName,CodeName,CodeTypeName,'Currency','Front Arena',StartDate),
Values(DatabaseName,CodeName,CodeTypeName,'ISIN','Front Arena',StartDate),
CodeName
Values('\\MZTSBATCH01\PUBLIC_GOLD','FA EQ MCC','Mapping Table','Table','Internal',StartDate),
Values(DatabaseName, MarketDataCode,'Bloomberg','Ask IntraDay','Bloomberg',StartDate)
).TRANSPOSE.FLATTEN()</Value>
          </CellDefinition>
          <CellDefinition p6:type="ConstantCellDefinition" CalculationEnabled="true" DataVisible="true" RowHidden="true" EndOfLine="false" xmlns:p6="http://www.w3.org/2001/XMLSchema-instance">
            <Range Top="53" Left="0" Bottom="53" Right="0" />
            <Value xmlns:q12="http://www.w3.org/2001/XMLSchema" p6:type="q12:string">Quality Index Ask Calculation</Value>
          </CellDefinition>
          <CellDefinition p6:type="FormulaCellDefinition" CalculationEnabled="true" DataVisible="true" RowHidden="true" EndOfLine="false" xmlns:p6="http://www.w3.org/2001/XMLSchema-instance">
            <Range Top="53" Left="1" Bottom="53" Right="1" />
            <Value>IF(QualityAsk = NULL OR ISERROR(QualityAsk),NULL,QualityAsk.Cells(1,2))</Value>
          </CellDefinition>
          <CellDefinition p6:type="FormulaCellDefinition" CalculationEnabled="true" DataVisible="true" RowHidden="true" EndOfLine="false" xmlns:p6="http://www.w3.org/2001/XMLSchema-instance">
            <Range Top="53" Left="2" Bottom="53" Right="2" />
            <Value>Values('PUBLIC_GOLD', 'Calculate QI 5D From Market data History', 'Calculation','Calculation','internal',StartDate)</Value>
          </CellDefinition>
          <CellDefinition p6:type="ConstantCellDefinition" CalculationEnabled="true" DataVisible="true" RowHidden="true" EndOfLine="false" xmlns:p6="http://www.w3.org/2001/XMLSchema-instance">
            <Range Top="54" Left="0" Bottom="54" Right="0" />
            <Value xmlns:q13="http://www.w3.org/2001/XMLSchema" p6:type="q13:string">Quality Index Bid Calculation</Value>
          </CellDefinition>
          <CellDefinition p6:type="FormulaCellDefinition" CalculationEnabled="true" DataVisible="true" RowHidden="true" EndOfLine="false" xmlns:p6="http://www.w3.org/2001/XMLSchema-instance">
            <Range Top="54" Left="1" Bottom="54" Right="1" />
            <Value>IF(QualityBid = NULL OR ISERROR(QualityBid),NULL,QualityBid.Cells(1,2))</Value>
          </CellDefinition>
          <CellDefinition p6:type="FormulaCellDefinition" CalculationEnabled="true" DataVisible="true" RowHidden="true" EndOfLine="false" xmlns:p6="http://www.w3.org/2001/XMLSchema-instance">
            <Range Top="54" Left="2" Bottom="54" Right="2" />
            <Value>Values('PUBLIC_GOLD', 'Calculate QI 5D From Market data History', 'Calculation','Calculation','internal',StartDate)</Value>
          </CellDefinition>
          <CellDefinition p6:type="ConstantCellDefinition" CalculationEnabled="true" DataVisible="true" RowHidden="false" EndOfLine="false" xmlns:p6="http://www.w3.org/2001/XMLSchema-instance">
            <Range Top="55" Left="0" Bottom="55" Right="0" />
            <Value xmlns:q14="http://www.w3.org/2001/XMLSchema" p6:type="q14:string">Reference Price Max</Value>
          </CellDefinition>
          <CellDefinition p6:type="FormulaCellDefinition" CalculationEnabled="true" DataVisible="true" RowHidden="false" EndOfLine="false" xmlns:p6="http://www.w3.org/2001/XMLSchema-instance">
            <Range Top="55" Left="1" Bottom="55" Right="1" />
            <Value>IF(TradeType ='HLB Warrant',IF(ISERROR(TradeQuotesMax),NULL,(0.0099*TradeQuotesMax).ROUND(2)),NULL)</Value>
          </CellDefinition>
          <CellDefinition p6:type="FormulaCellDefinition" CalculationEnabled="true" DataVisible="true" RowHidden="false" EndOfLine="false" xmlns:p6="http://www.w3.org/2001/XMLSchema-instance">
            <Range Top="55" Left="2" Bottom="55" Right="2" />
            <Value>Values(
Values(DatabaseName,CodeName,CodeTypeName,'TradeDateTime','Front Arena',StartDate),
Values(DatabaseName,CodeName,CodeTypeName,'CounterPArty','Front Arena',StartDate),
Values(DatabaseName,CodeName,CodeTypeName,'Instrument','Front Arena',StartDate),
Values(DatabaseName,CodeName,CodeTypeName,'Currency','Front Arena',StartDate),
Values(DatabaseName,CodeName,CodeTypeName,'ISIN','Front Arena',StartDate),
CodeName
Values('\\MZTSBATCH01\PUBLIC_GOLD','FA EQ MCC','Mapping Table','Table','Internal',StartDate),
Values(DatabaseName, MarketDataCode,'Bloomberg','Ask IntraDay','Bloomberg',StartDate)
).TRANSPOSE.FLATTEN()</Value>
          </CellDefinition>
          <CellDefinition p6:type="ConstantCellDefinition" CalculationEnabled="true" DataVisible="true" RowHidden="false" EndOfLine="false" xmlns:p6="http://www.w3.org/2001/XMLSchema-instance">
            <Range Top="56" Left="0" Bottom="56" Right="0" />
            <Value xmlns:q15="http://www.w3.org/2001/XMLSchema" p6:type="q15:string">Reference Price Min</Value>
          </CellDefinition>
          <CellDefinition p6:type="FormulaCellDefinition" CalculationEnabled="true" DataVisible="true" RowHidden="false" EndOfLine="false" xmlns:p6="http://www.w3.org/2001/XMLSchema-instance">
            <Range Top="56" Left="1" Bottom="56" Right="1" />
            <Value>IF(TradeType ='HLB Warrant',IF(ISERROR(TradeQuotesMin),NULL, (0.0099*TradeQuotesMin).ROUND(2)),NULL)</Value>
          </CellDefinition>
          <CellDefinition p6:type="FormulaCellDefinition" CalculationEnabled="true" DataVisible="true" RowHidden="false" EndOfLine="false" xmlns:p6="http://www.w3.org/2001/XMLSchema-instance">
            <Range Top="56" Left="2" Bottom="56" Right="2" />
            <Value>Values(
Values(DatabaseName,CodeName,CodeTypeName,'TradeDateTime','Front Arena',StartDate),
Values(DatabaseName,CodeName,CodeTypeName,'CounterPArty','Front Arena',StartDate),
Values(DatabaseName,CodeName,CodeTypeName,'Instrument','Front Arena',StartDate),
Values(DatabaseName,CodeName,CodeTypeName,'Currency','Front Arena',StartDate),
Values(DatabaseName,CodeName,CodeTypeName,'ISIN','Front Arena',StartDate),
CodeName
Values('\\MZTSBATCH01\PUBLIC_GOLD','FA EQ MCC','Mapping Table','Table','Internal',StartDate),
Values(DatabaseName, MarketDataCode,'Bloomberg','Ask IntraDay','Bloomberg',StartDate)
).TRANSPOSE.FLATTEN()</Value>
          </CellDefinition>
          <CellDefinition p6:type="ConstantCellDefinition" CalculationEnabled="true" DataVisible="true" RowHidden="false" EndOfLine="false" xmlns:p6="http://www.w3.org/2001/XMLSchema-instance">
            <Range Top="57" Left="0" Bottom="57" Right="0" />
            <Value xmlns:q16="http://www.w3.org/2001/XMLSchema" p6:type="q16:string">Reference Price Ask</Value>
          </CellDefinition>
          <CellDefinition p6:type="FormulaCellDefinition" CalculationEnabled="true" DataVisible="true" RowHidden="false" EndOfLine="false" xmlns:p6="http://www.w3.org/2001/XMLSchema-instance">
            <Range Top="57" Left="1" Bottom="57" Right="1" />
            <Value>IF(ISERROR(MaxAsk),NULL,MaxAsk)</Value>
          </CellDefinition>
          <CellDefinition p6:type="FormulaCellDefinition" CalculationEnabled="true" DataVisible="true" RowHidden="false" EndOfLine="false" xmlns:p6="http://www.w3.org/2001/XMLSchema-instance">
            <Range Top="57" Left="2" Bottom="57" Right="2" />
            <Value>Values(
Values(DatabaseName,CodeName,CodeTypeName,'TradeDateTime','Front Arena',StartDate),
Values(DatabaseName,CodeName,CodeTypeName,'CounterPArty','Front Arena',StartDate),
Values(DatabaseName,CodeName,CodeTypeName,'Instrument','Front Arena',StartDate),
Values(DatabaseName,CodeName,CodeTypeName,'Currency','Front Arena',StartDate),
Values(DatabaseName,CodeName,CodeTypeName,'ISIN','Front Arena',StartDate),
CodeName
Values('\\MZTSBATCH01\PUBLIC_GOLD','FA EQ MCC','Mapping Table','Table','Internal',StartDate),
Values(DatabaseName, MarketDataCode,'Bloomberg','Ask IntraDay','Bloomberg',StartDate)
).TRANSPOSE.FLATTEN()</Value>
          </CellDefinition>
          <CellDefinition p6:type="ConstantCellDefinition" CalculationEnabled="true" DataVisible="true" RowHidden="true" EndOfLine="false" xmlns:p6="http://www.w3.org/2001/XMLSchema-instance">
            <Range Top="58" Left="0" Bottom="58" Right="0" />
            <Value xmlns:q17="http://www.w3.org/2001/XMLSchema" p6:type="q17:string">Quality Index Ask</Value>
          </CellDefinition>
          <CellDefinition p6:type="FormulaCellDefinition" CalculationEnabled="true" DataVisible="true" RowHidden="true" EndOfLine="false" xmlns:p6="http://www.w3.org/2001/XMLSchema-instance">
            <Range Top="58" Left="1" Bottom="58" Right="1" />
            <Value>IF(QualityAsk = NULL OR ISERROR(QualityAsk),NULL,QualityAsk.Cells(1,1))</Value>
          </CellDefinition>
          <CellDefinition p6:type="FormulaCellDefinition" CalculationEnabled="true" DataVisible="true" RowHidden="true" EndOfLine="false" xmlns:p6="http://www.w3.org/2001/XMLSchema-instance">
            <Range Top="58" Left="2" Bottom="58" Right="2" />
            <Value>Values('PUBLIC_GOLD', 'Calculate QI 5D From Market data History', 'Calculation','Calculation','internal',StartDate)</Value>
          </CellDefinition>
          <CellDefinition p6:type="ConstantCellDefinition" CalculationEnabled="true" DataVisible="true" RowHidden="false" EndOfLine="false" xmlns:p6="http://www.w3.org/2001/XMLSchema-instance">
            <Range Top="59" Left="0" Bottom="59" Right="0" />
            <Value xmlns:q18="http://www.w3.org/2001/XMLSchema" p6:type="q18:string">Reference Price Bid</Value>
          </CellDefinition>
          <CellDefinition p6:type="FormulaCellDefinition" CalculationEnabled="true" DataVisible="true" RowHidden="false" EndOfLine="false" xmlns:p6="http://www.w3.org/2001/XMLSchema-instance">
            <Range Top="59" Left="1" Bottom="59" Right="1" />
            <Value>IF(ISERROR(MinBid),NULL,MinBid)</Value>
          </CellDefinition>
          <CellDefinition p6:type="FormulaCellDefinition" CalculationEnabled="true" DataVisible="true" RowHidden="false" EndOfLine="false" xmlns:p6="http://www.w3.org/2001/XMLSchema-instance">
            <Range Top="59" Left="2" Bottom="59" Right="2" />
            <Value>Values(
Values(DatabaseName,CodeName,CodeTypeName,'TradeDateTime','Front Arena',StartDate),
Values(DatabaseName,CodeName,CodeTypeName,'CounterPArty','Front Arena',StartDate),
Values(DatabaseName,CodeName,CodeTypeName,'Instrument','Front Arena',StartDate),
Values(DatabaseName,CodeName,CodeTypeName,'Currency','Front Arena',StartDate),
Values(DatabaseName,CodeName,CodeTypeName,'ISIN','Front Arena',StartDate),
CodeName
Values('\\MZTSBATCH01\PUBLIC_GOLD','FA EQ MCC','Mapping Table','Table','Internal',StartDate),
Values(DatabaseName, MarketDataCode,'Bloomberg','Ask IntraDay','Bloomberg',StartDate)
).TRANSPOSE.FLATTEN()</Value>
          </CellDefinition>
          <CellDefinition p6:type="ConstantCellDefinition" CalculationEnabled="true" DataVisible="true" RowHidden="false" EndOfLine="false" xmlns:p6="http://www.w3.org/2001/XMLSchema-instance">
            <Range Top="60" Left="0" Bottom="60" Right="0" />
            <Value xmlns:q19="http://www.w3.org/2001/XMLSchema" p6:type="q19:string">Quality Index Bid</Value>
          </CellDefinition>
          <CellDefinition p6:type="FormulaCellDefinition" CalculationEnabled="true" DataVisible="true" RowHidden="false" EndOfLine="false" xmlns:p6="http://www.w3.org/2001/XMLSchema-instance">
            <Range Top="60" Left="1" Bottom="60" Right="1" />
            <Value>IF(QualityBid = NULL OR ISERROR(QualityBid),NULL,QualityBid.Cells(1,1))</Value>
          </CellDefinition>
          <CellDefinition p6:type="FormulaCellDefinition" CalculationEnabled="true" DataVisible="true" RowHidden="false" EndOfLine="false" xmlns:p6="http://www.w3.org/2001/XMLSchema-instance">
            <Range Top="60" Left="2" Bottom="60" Right="2" />
            <Value>Values('PUBLIC_GOLD', 'Calculate QI 5D From Market data History', 'Calculation','Calculation','internal',StartDate)</Value>
          </CellDefinition>
          <CellDefinition p6:type="ConstantCellDefinition" CalculationEnabled="true" DataVisible="true" RowHidden="false" EndOfLine="false" xmlns:p6="http://www.w3.org/2001/XMLSchema-instance">
            <Range Top="61" Left="0" Bottom="61" Right="0" />
            <Value xmlns:q20="http://www.w3.org/2001/XMLSchema" p6:type="q20:string">Value Under Test</Value>
          </CellDefinition>
          <CellDefinition p6:type="FormulaCellDefinition" CalculationEnabled="true" DataVisible="true" RowHidden="false" EndOfLine="false" xmlns:p6="http://www.w3.org/2001/XMLSchema-instance">
            <Range Top="61" Left="1" Bottom="61" Right="1" />
            <Value>Tradeitem.Trade Price</Value>
          </CellDefinition>
          <CellDefinition CalculationEnabled="true" DataVisible="true" RowHidden="false" EndOfLine="false">
            <Range Top="57" Left="3" Bottom="57" Right="3" />
          </CellDefinition>
          <CellDefinition CalculationEnabled="true" DataVisible="true" RowHidden="false" EndOfLine="false">
            <Range Top="59" Left="3" Bottom="59" Right="3" />
          </CellDefinition>
          <CellDefinition p6:type="FormulaCellDefinition" CalculationEnabled="true" DataVisible="true" RowHidden="false" EndOfLine="false" xmlns:p6="http://www.w3.org/2001/XMLSchema-instance">
            <Range Top="47" Left="2" Bottom="47" Right="2" />
            <Value>QualityAsk</Value>
          </CellDefinition>
          <CellDefinition p6:type="FormulaCellDefinition" CalculationEnabled="true" DataVisible="true" RowHidden="false" EndOfLine="false" xmlns:p6="http://www.w3.org/2001/XMLSchema-instance">
            <Range Top="48" Left="2" Bottom="48" Right="2" />
            <Value>QualityBid</Value>
          </CellDefinition>
          <CellDefinition p6:type="ConstantCellDefinition" CalculationEnabled="true" DataVisible="true" RowHidden="false" EndOfLine="false" xmlns:p6="http://www.w3.org/2001/XMLSchema-instance">
            <Range Top="0" Left="1" Bottom="0" Right="1" />
            <Value xmlns:q21="http://www.w3.org/2001/XMLSchema" p6:type="q21:string">Front Arena Common Stock/Right Reference Value</Value>
          </CellDefinition>
          <CellDefinition p6:type="ConstantCellDefinition" CalculationEnabled="true" DataVisible="true" RowHidden="false" EndOfLine="false" xmlns:p6="http://www.w3.org/2001/XMLSchema-instance">
            <Range Top="2" Left="0" Bottom="2" Right="0" />
            <Value xmlns:q22="http://www.w3.org/2001/XMLSchema" p6:type="q22:string">DatabaseName</Value>
          </CellDefinition>
          <CellDefinition p6:type="ConstantCellDefinition" CalculationEnabled="true" DataVisible="true" RowHidden="false" EndOfLine="false" xmlns:p6="http://www.w3.org/2001/XMLSchema-instance">
            <Range Top="3" Left="0" Bottom="3" Right="0" />
            <Value xmlns:q23="http://www.w3.org/2001/XMLSchema" p6:type="q23:string">CodeName</Value>
          </CellDefinition>
          <CellDefinition p6:type="ConstantCellDefinition" CalculationEnabled="true" DataVisible="true" RowHidden="false" EndOfLine="false" xmlns:p6="http://www.w3.org/2001/XMLSchema-instance">
            <Range Top="4" Left="0" Bottom="4" Right="0" />
            <Value xmlns:q24="http://www.w3.org/2001/XMLSchema" p6:type="q24:string">CodeTypeName</Value>
          </CellDefinition>
          <CellDefinition p6:type="ConstantCellDefinition" CalculationEnabled="true" DataVisible="true" RowHidden="false" EndOfLine="false" xmlns:p6="http://www.w3.org/2001/XMLSchema-instance">
            <Range Top="5" Left="0" Bottom="5" Right="0" />
            <Value xmlns:q25="http://www.w3.org/2001/XMLSchema" p6:type="q25:string">TargetProperty</Value>
          </CellDefinition>
          <CellDefinition p6:type="ConstantCellDefinition" CalculationEnabled="true" DataVisible="true" RowHidden="false" EndOfLine="false" xmlns:p6="http://www.w3.org/2001/XMLSchema-instance">
            <Range Top="6" Left="0" Bottom="6" Right="0" />
            <Value xmlns:q26="http://www.w3.org/2001/XMLSchema" p6:type="q26:string">StartDate</Value>
          </CellDefinition>
          <CellDefinition p6:type="ConstantCellDefinition" CalculationEnabled="true" DataVisible="true" RowHidden="false" EndOfLine="false" xmlns:p6="http://www.w3.org/2001/XMLSchema-instance">
            <Range Top="7" Left="0" Bottom="7" Right="0" />
            <Value xmlns:q27="http://www.w3.org/2001/XMLSchema" p6:type="q27:string">EndDate</Value>
          </CellDefinition>
          <CellDefinition p6:type="ConstantCellDefinition" CalculationEnabled="true" DataVisible="true" RowHidden="false" EndOfLine="false" xmlns:p6="http://www.w3.org/2001/XMLSchema-instance">
            <Range Top="8" Left="0" Bottom="8" Right="0" />
            <Value xmlns:q28="http://www.w3.org/2001/XMLSchema" p6:type="q28:string">TargetDataSource</Value>
          </CellDefinition>
          <CellDefinition p6:type="ConstantCellDefinition" CalculationEnabled="true" DataVisible="true" RowHidden="false" EndOfLine="false" xmlns:p6="http://www.w3.org/2001/XMLSchema-instance">
            <Range Top="15" Left="0" Bottom="15" Right="0" />
            <Value xmlns:q29="http://www.w3.org/2001/XMLSchema" p6:type="q29:string">Tradeitem</Value>
          </CellDefinition>
          <CellDefinition p6:type="ConstantCellDefinition" CalculationEnabled="true" DataVisible="true" RowHidden="false" EndOfLine="false" xmlns:p6="http://www.w3.org/2001/XMLSchema-instance">
            <Range Top="21" Left="0" Bottom="21" Right="0" />
            <Value xmlns:q30="http://www.w3.org/2001/XMLSchema" p6:type="q30:string">Instrument</Value>
          </CellDefinition>
          <CellDefinition p6:type="ConstantCellDefinition" CalculationEnabled="true" DataVisible="true" RowHidden="false" EndOfLine="false" xmlns:p6="http://www.w3.org/2001/XMLSchema-instance">
            <Range Top="22" Left="0" Bottom="22" Right="0" />
            <Value xmlns:q31="http://www.w3.org/2001/XMLSchema" p6:type="q31:string">Currency</Value>
          </CellDefinition>
          <CellDefinition p6:type="ConstantCellDefinition" CalculationEnabled="true" DataVisible="true" RowHidden="false" EndOfLine="false" xmlns:p6="http://www.w3.org/2001/XMLSchema-instance">
            <Range Top="23" Left="0" Bottom="23" Right="0" />
            <Value xmlns:q32="http://www.w3.org/2001/XMLSchema" p6:type="q32:string">ISIN</Value>
          </CellDefinition>
          <CellDefinition p6:type="ConstantCellDefinition" CalculationEnabled="true" DataVisible="true" RowHidden="false" EndOfLine="false" xmlns:p6="http://www.w3.org/2001/XMLSchema-instance">
            <Range Top="24" Left="0" Bottom="24" Right="0" />
            <Value xmlns:q33="http://www.w3.org/2001/XMLSchema" p6:type="q33:string">Market</Value>
          </CellDefinition>
          <CellDefinition p6:type="ConstantCellDefinition" CalculationEnabled="true" DataVisible="true" RowHidden="false" EndOfLine="false" xmlns:p6="http://www.w3.org/2001/XMLSchema-instance">
            <Range Top="26" Left="0" Bottom="26" Right="0" />
            <Value xmlns:q34="http://www.w3.org/2001/XMLSchema" p6:type="q34:string">Mapping Table</Value>
          </CellDefinition>
          <CellDefinition p6:type="ConstantCellDefinition" CalculationEnabled="true" DataVisible="true" RowHidden="false" EndOfLine="false" xmlns:p6="http://www.w3.org/2001/XMLSchema-instance">
            <Range Top="28" Left="0" Bottom="28" Right="0" />
            <Value xmlns:q35="http://www.w3.org/2001/XMLSchema" p6:type="q35:string">MappingTableStockcode</Value>
          </CellDefinition>
          <CellDefinition p6:type="ConstantCellDefinition" CalculationEnabled="true" DataVisible="true" RowHidden="false" EndOfLine="false" xmlns:p6="http://www.w3.org/2001/XMLSchema-instance">
            <Range Top="38" Left="0" Bottom="38" Right="0" />
            <Value xmlns:q36="http://www.w3.org/2001/XMLSchema" p6:type="q36:string">MarketDataItem</Value>
          </CellDefinition>
          <CellDefinition p6:type="ConstantCellDefinition" CalculationEnabled="true" DataVisible="true" RowHidden="false" EndOfLine="false" xmlns:p6="http://www.w3.org/2001/XMLSchema-instance">
            <Range Top="27" Left="0" Bottom="27" Right="0" />
            <Value xmlns:q37="http://www.w3.org/2001/XMLSchema" p6:type="q37:string">IS_GR_Equity</Value>
          </CellDefinition>
          <CellDefinition p6:type="ConstantCellDefinition" CalculationEnabled="true" DataVisible="true" RowHidden="false" EndOfLine="false" xmlns:p6="http://www.w3.org/2001/XMLSchema-instance">
            <Range Top="29" Left="0" Bottom="29" Right="0" />
            <Value xmlns:q38="http://www.w3.org/2001/XMLSchema" p6:type="q38:string">AdjustCodeForGREquity</Value>
          </CellDefinition>
          <CellDefinition p6:type="ConstantCellDefinition" CalculationEnabled="true" DataVisible="true" RowHidden="false" EndOfLine="false" xmlns:p6="http://www.w3.org/2001/XMLSchema-instance">
            <Range Top="20" Left="0" Bottom="20" Right="0" />
            <Value xmlns:q39="http://www.w3.org/2001/XMLSchema" p6:type="q39:string">Counterparty</Value>
          </CellDefinition>
          <CellDefinition p6:type="ConstantCellDefinition" CalculationEnabled="true" DataVisible="true" RowHidden="false" EndOfLine="false" xmlns:p6="http://www.w3.org/2001/XMLSchema-instance">
            <Range Top="16" Left="0" Bottom="16" Right="0" />
            <Value xmlns:q40="http://www.w3.org/2001/XMLSchema" p6:type="q40:string">TradeDateTime</Value>
          </CellDefinition>
          <CellDefinition p6:type="ConstantCellDefinition" CalculationEnabled="true" DataVisible="true" RowHidden="false" EndOfLine="false" xmlns:p6="http://www.w3.org/2001/XMLSchema-instance">
            <Range Top="10" Left="0" Bottom="10" Right="0" />
            <Value xmlns:q41="http://www.w3.org/2001/XMLSchema" p6:type="q41:string">MaximumAge</Value>
          </CellDefinition>
          <CellDefinition p6:type="ConstantCellDefinition" CalculationEnabled="true" DataVisible="true" RowHidden="false" EndOfLine="false" xmlns:p6="http://www.w3.org/2001/XMLSchema-instance">
            <Range Top="39" Left="0" Bottom="39" Right="0" />
            <Value xmlns:q42="http://www.w3.org/2001/XMLSchema" p6:type="q42:string">MarketdataStartTime</Value>
          </CellDefinition>
          <CellDefinition p6:type="ConstantCellDefinition" CalculationEnabled="true" DataVisible="true" RowHidden="false" EndOfLine="false" xmlns:p6="http://www.w3.org/2001/XMLSchema-instance">
            <Range Top="40" Left="0" Bottom="40" Right="0" />
            <Value xmlns:q43="http://www.w3.org/2001/XMLSchema" p6:type="q43:string">MarketDataEndTime</Value>
          </CellDefinition>
          <CellDefinition p6:type="ConstantCellDefinition" CalculationEnabled="true" DataVisible="true" RowHidden="false" EndOfLine="false" xmlns:p6="http://www.w3.org/2001/XMLSchema-instance">
            <Range Top="41" Left="0" Bottom="41" Right="0" />
            <Value xmlns:q44="http://www.w3.org/2001/XMLSchema" p6:type="q44:string">Ask</Value>
          </CellDefinition>
          <CellDefinition p6:type="ConstantCellDefinition" CalculationEnabled="true" DataVisible="true" RowHidden="false" EndOfLine="false" xmlns:p6="http://www.w3.org/2001/XMLSchema-instance">
            <Range Top="42" Left="0" Bottom="42" Right="0" />
            <Value xmlns:q45="http://www.w3.org/2001/XMLSchema" p6:type="q45:string">Bid</Value>
          </CellDefinition>
          <CellDefinition p6:type="ConstantCellDefinition" CalculationEnabled="true" DataVisible="true" RowHidden="false" EndOfLine="false" xmlns:p6="http://www.w3.org/2001/XMLSchema-instance">
            <Range Top="43" Left="0" Bottom="43" Right="0" />
            <Value xmlns:q46="http://www.w3.org/2001/XMLSchema" p6:type="q46:string">MaxAsk</Value>
          </CellDefinition>
          <CellDefinition p6:type="ConstantCellDefinition" CalculationEnabled="true" DataVisible="true" RowHidden="false" EndOfLine="false" xmlns:p6="http://www.w3.org/2001/XMLSchema-instance">
            <Range Top="44" Left="0" Bottom="44" Right="0" />
            <Value xmlns:q47="http://www.w3.org/2001/XMLSchema" p6:type="q47:string">MinBid</Value>
          </CellDefinition>
          <CellDefinition p6:type="ConstantCellDefinition" CalculationEnabled="true" DataVisible="true" RowHidden="false" EndOfLine="false" xmlns:p6="http://www.w3.org/2001/XMLSchema-instance">
            <Range Top="11" Left="0" Bottom="11" Right="0" />
            <Value xmlns:q48="http://www.w3.org/2001/XMLSchema" p6:type="q48:string">TradeType</Value>
          </CellDefinition>
          <CellDefinition p6:type="ConstantCellDefinition" CalculationEnabled="true" DataVisible="true" RowHidden="false" EndOfLine="false" xmlns:p6="http://www.w3.org/2001/XMLSchema-instance">
            <Range Top="31" Left="0" Bottom="31" Right="0" />
            <Value xmlns:q49="http://www.w3.org/2001/XMLSchema" p6:type="q49:string">StockCode</Value>
          </CellDefinition>
          <CellDefinition p6:type="ConstantCellDefinition" CalculationEnabled="true" DataVisible="true" RowHidden="false" EndOfLine="false" xmlns:p6="http://www.w3.org/2001/XMLSchema-instance">
            <Range Top="32" Left="0" Bottom="32" Right="0" />
            <Value xmlns:q50="http://www.w3.org/2001/XMLSchema" p6:type="q50:string">WarrantCode</Value>
          </CellDefinition>
          <CellDefinition p6:type="ConstantCellDefinition" CalculationEnabled="true" DataVisible="true" RowHidden="false" EndOfLine="false" xmlns:p6="http://www.w3.org/2001/XMLSchema-instance">
            <Range Top="33" Left="0" Bottom="33" Right="0" />
            <Value xmlns:q51="http://www.w3.org/2001/XMLSchema" p6:type="q51:string">OptionCode</Value>
          </CellDefinition>
          <CellDefinition p6:type="ConstantCellDefinition" CalculationEnabled="true" DataVisible="true" RowHidden="false" EndOfLine="false" xmlns:p6="http://www.w3.org/2001/XMLSchema-instance">
            <Range Top="34" Left="0" Bottom="34" Right="0" />
            <Value xmlns:q52="http://www.w3.org/2001/XMLSchema" p6:type="q52:string">FuturesCode</Value>
          </CellDefinition>
          <CellDefinition p6:type="ConstantCellDefinition" CalculationEnabled="true" DataVisible="true" RowHidden="false" EndOfLine="false" xmlns:p6="http://www.w3.org/2001/XMLSchema-instance">
            <Range Top="36" Left="0" Bottom="36" Right="0" />
            <Value xmlns:q53="http://www.w3.org/2001/XMLSchema" p6:type="q53:string">MarketDataCode</Value>
          </CellDefinition>
          <CellDefinition p6:type="ConstantCellDefinition" CalculationEnabled="true" DataVisible="true" RowHidden="false" EndOfLine="false" xmlns:p6="http://www.w3.org/2001/XMLSchema-instance">
            <Range Top="2" Left="2" Bottom="2" Right="2" />
            <Value xmlns:q54="http://www.w3.org/2001/XMLSchema" p6:type="q54:string">2475919_Buy</Value>
          </CellDefinition>
          <CellDefinition p6:type="ConstantCellDefinition" CalculationEnabled="true" DataVisible="true" RowHidden="false" EndOfLine="false" xmlns:p6="http://www.w3.org/2001/XMLSchema-instance">
            <Range Top="1" Left="2" Bottom="1" Right="2" />
            <Value xmlns:q55="http://www.w3.org/2001/XMLSchema" p6:type="q55:string">Stock</Value>
          </CellDefinition>
          <CellDefinition p6:type="ConstantCellDefinition" CalculationEnabled="true" DataVisible="true" RowHidden="false" EndOfLine="false" xmlns:p6="http://www.w3.org/2001/XMLSchema-instance">
            <Range Top="35" Left="0" Bottom="35" Right="0" />
            <Value xmlns:q56="http://www.w3.org/2001/XMLSchema" p6:type="q56:string">ETFCode</Value>
          </CellDefinition>
          <CellDefinition p6:type="ConstantCellDefinition" CalculationEnabled="true" DataVisible="true" RowHidden="false" EndOfLine="false" xmlns:p6="http://www.w3.org/2001/XMLSchema-instance">
            <Range Top="37" Left="0" Bottom="37" Right="0" />
            <Value xmlns:q57="http://www.w3.org/2001/XMLSchema" p6:type="q57:string">MarketDataSource</Value>
          </CellDefinition>
          <CellDefinition p6:type="FormulaCellDefinition" CalculationEnabled="true" DataVisible="true" RowHidden="false" EndOfLine="false" xmlns:p6="http://www.w3.org/2001/XMLSchema-instance">
            <Range Top="42" Left="2" Bottom="42" Right="2" />
            <Value>MarketDataItem.Values(|Ask Intraday|.Data(MarketdataStartTime,MarketDataEndTime))</Value>
          </CellDefinition>
          <CellDefinition p6:type="ConstantCellDefinition" CalculationEnabled="true" DataVisible="true" RowHidden="false" EndOfLine="false" xmlns:p6="http://www.w3.org/2001/XMLSchema-instance">
            <Range Top="47" Left="0" Bottom="47" Right="0" />
            <Value xmlns:q58="http://www.w3.org/2001/XMLSchema" p6:type="q58:string">Quality Index Ask</Value>
          </CellDefinition>
          <CellDefinition p6:type="ConstantCellDefinition" CalculationEnabled="true" DataVisible="true" RowHidden="false" EndOfLine="false" xmlns:p6="http://www.w3.org/2001/XMLSchema-instance">
            <Range Top="48" Left="0" Bottom="48" Right="0" />
            <Value xmlns:q59="http://www.w3.org/2001/XMLSchema" p6:type="q59:string">Quality Index Bid</Value>
          </CellDefinition>
          <CellDefinition p6:type="ConstantCellDefinition" CalculationEnabled="true" DataVisible="true" RowHidden="false" EndOfLine="false" xmlns:p6="http://www.w3.org/2001/XMLSchema-instance">
            <Range Top="63" Left="0" Bottom="63" Right="0" />
            <Value xmlns:q60="http://www.w3.org/2001/XMLSchema" p6:type="q60:string">InputAudit</Value>
          </CellDefinition>
          <CellDefinition p6:type="FormulaCellDefinition" CalculationEnabled="true" DataVisible="true" RowHidden="false" EndOfLine="false" xmlns:p6="http://www.w3.org/2001/XMLSchema-instance">
            <Range Top="47" Left="3" Bottom="47" Right="3" />
            <Value>Item('PUBLIC_GOLD', 'Copy of Calculate QI From Market data History', 'Calculation' ).CalculatiON.SetValues( 'DailyTimeSeries', MarketDataItem.End of Day Ask, 'TodaysPrice', D58 ).GetValues( 'QualityIndex', 'QualityIndexCalculation' )</Value>
          </CellDefinition>
          <CellDefinition p6:type="FormulaCellDefinition" CalculationEnabled="true" DataVisible="true" RowHidden="false" EndOfLine="false" xmlns:p6="http://www.w3.org/2001/XMLSchema-instance">
            <Range Top="48" Left="3" Bottom="48" Right="3" />
            <Value>Item('PUBLIC_GOLD', 'Copy of Calculate QI From Market data History', 'Calculation' ).CalculatiON.SetValues( 'DailyTimeSeries', MarketDataItem.End of Day Bid, 'TodaysPrice', D60 ).GetValues( 'QualityIndex', 'QualityIndexCalculation').Cells(1,1)</Value>
          </CellDefinition>
          <CellDefinition p6:type="ConstantCellDefinition" CalculationEnabled="true" DataVisible="true" RowHidden="false" EndOfLine="false" xmlns:p6="http://www.w3.org/2001/XMLSchema-instance">
            <Range Top="3" Left="3" Bottom="3" Right="3" />
            <Value xmlns:q61="http://www.w3.org/2001/XMLSchema" p6:type="q61:string">2627232_Buy</Value>
          </CellDefinition>
          <CellDefinition p6:type="ConstantCellDefinition" CalculationEnabled="true" DataVisible="true" RowHidden="false" EndOfLine="false" xmlns:p6="http://www.w3.org/2001/XMLSchema-instance">
            <Range Top="6" Left="3" Bottom="6" Right="3" />
            <Value xmlns:q62="http://www.w3.org/2001/XMLSchema" p6:type="q62:dateTime">2018-08-28T00:00:00</Value>
          </CellDefinition>
          <CellDefinition p6:type="ConstantCellDefinition" CalculationEnabled="true" DataVisible="true" RowHidden="false" EndOfLine="false" xmlns:p6="http://www.w3.org/2001/XMLSchema-instance">
            <Range Top="45" Left="0" Bottom="45" Right="0" />
            <Value xmlns:q63="http://www.w3.org/2001/XMLSchema" p6:type="q63:string">Trade Quotes Max</Value>
          </CellDefinition>
          <CellDefinition p6:type="ConstantCellDefinition" CalculationEnabled="true" DataVisible="true" RowHidden="false" EndOfLine="false" xmlns:p6="http://www.w3.org/2001/XMLSchema-instance">
            <Range Top="46" Left="0" Bottom="46" Right="0" />
            <Value xmlns:q64="http://www.w3.org/2001/XMLSchema" p6:type="q64:string">Trade Quotes Min</Value>
          </CellDefinition>
          <CellDefinition p6:type="ConstantCellDefinition" CalculationEnabled="true" DataVisible="true" RowHidden="false" EndOfLine="false" xmlns:p6="http://www.w3.org/2001/XMLSchema-instance">
            <Range Top="18" Left="0" Bottom="18" Right="0" />
            <Value xmlns:q65="http://www.w3.org/2001/XMLSchema" p6:type="q65:string">Start DateTime</Value>
          </CellDefinition>
          <CellDefinition p6:type="ConstantCellDefinition" CalculationEnabled="true" DataVisible="true" RowHidden="false" EndOfLine="false" xmlns:p6="http://www.w3.org/2001/XMLSchema-instance">
            <Range Top="19" Left="0" Bottom="19" Right="0" />
            <Value xmlns:q66="http://www.w3.org/2001/XMLSchema" p6:type="q66:string">End DateTime</Value>
          </CellDefinition>
          <CellDefinition p6:type="ConstantCellDefinition" CalculationEnabled="true" DataVisible="true" RowHidden="false" EndOfLine="false" xmlns:p6="http://www.w3.org/2001/XMLSchema-instance">
            <Range Top="12" Left="0" Bottom="12" Right="0" />
            <Value xmlns:q67="http://www.w3.org/2001/XMLSchema" p6:type="q67:string">RequestItemCode</Value>
          </CellDefinition>
          <CellDefinition p6:type="ConstantCellDefinition" CalculationEnabled="true" DataVisible="true" RowHidden="false" EndOfLine="false" xmlns:p6="http://www.w3.org/2001/XMLSchema-instance">
            <Range Top="17" Left="0" Bottom="17" Right="0" />
            <Value xmlns:q68="http://www.w3.org/2001/XMLSchema" p6:type="q68:string">Request Item</Value>
          </CellDefinition>
          <CellDefinition p6:type="ConstantCellDefinition" CalculationEnabled="true" DataVisible="true" RowHidden="false" EndOfLine="false" xmlns:p6="http://www.w3.org/2001/XMLSchema-instance">
            <Range Top="3" Left="2" Bottom="3" Right="2" />
            <Value xmlns:q69="http://www.w3.org/2001/XMLSchema" p6:type="q69:string">20181023_2676559_Buy</Value>
          </CellDefinition>
          <CellDefinition CalculationEnabled="true" DataVisible="true" RowHidden="false" EndOfLine="false">
            <Range Top="56" Left="3" Bottom="56" Right="3" />
          </CellDefinition>
          <CellDefinition CalculationEnabled="true" DataVisible="true" RowHidden="false" EndOfLine="false">
            <Range Top="56" Left="4" Bottom="56" Right="4" />
          </CellDefinition>
          <CellDefinition CalculationEnabled="true" DataVisible="true" RowHidden="true" EndOfLine="false">
            <Range Top="53" Left="3" Bottom="53" Right="3" />
          </CellDefinition>
          <CellDefinition CalculationEnabled="true" DataVisible="true" RowHidden="true" EndOfLine="false">
            <Range Top="53" Left="4" Bottom="53" Right="4" />
          </CellDefinition>
          <CellDefinition CalculationEnabled="true" DataVisible="true" RowHidden="true" EndOfLine="false">
            <Range Top="54" Left="3" Bottom="54" Right="3" />
          </CellDefinition>
          <CellDefinition CalculationEnabled="true" DataVisible="true" RowHidden="true" EndOfLine="false">
            <Range Top="54" Left="4" Bottom="54" Right="4" />
          </CellDefinition>
          <CellDefinition CalculationEnabled="true" DataVisible="true" RowHidden="true" EndOfLine="false">
            <Range Top="58" Left="4" Bottom="58" Right="4" />
          </CellDefinition>
          <CellDefinition p6:type="ConstantCellDefinition" CalculationEnabled="true" DataVisible="true" RowHidden="false" EndOfLine="false" xmlns:p6="http://www.w3.org/2001/XMLSchema-instance">
            <Range Top="3" Left="4" Bottom="3" Right="4" />
            <Value xmlns:q70="http://www.w3.org/2001/XMLSchema" p6:type="q70:string">2711291_Buy</Value>
          </CellDefinition>
        </Cells>
      </Xenomorph.Generic.Formula>
    </Property>
  </Item>
</Category>
